tesseract_positional/__init__.py
tesseract_positional/cmd_line.py
tesseract_positional/positional_ocr.py
tesseract_positional-0.1.2.dist-info/LICENSE
tesseract_positional-0.1.2.dist-info/METADATA
tesseract_positional-0.1.2.dist-info/WHEEL
tesseract_positional-0.1.2.dist-info/entry_points.txt
tesseract_positional-0.1.2.dist-info/top_level.txt
tesseract_positional-0.1.2.dist-info/RECORD
