Metadata-Version: 2.1
Name: tesseract-positional
Version: 0.1.2
Summary: Tool to save positional OCR data to a text file
Author-email: Travis Kessler <travis.j.kessler@gmail.com>
Project-URL: Homepage, https://github.com/tjkessler/tesseract-positional
Project-URL: Bug Tracker, https://github.com/tjkessler/tesseract-positional/issues
Classifier: Programming Language :: Python :: 3.11
Classifier: License :: OSI Approved :: Apache Software License
Classifier: Operating System :: OS Independent
Requires-Python: >=3.11
License-File: LICENSE
Requires-Dist: pytesseract (==0.3.10)
